muttfuzz/analyze_results.py
muttfuzz/apply_mutant.py
muttfuzz/fuzz.py
muttfuzz/fuzzutil.py
muttfuzz/libfuzzer_prune.py
muttfuzz/mutate.py
muttfuzz-1.2.28.dist-info/METADATA
muttfuzz-1.2.28.dist-info/WHEEL
muttfuzz-1.2.28.dist-info/entry_points.txt
muttfuzz-1.2.28.dist-info/top_level.txt
muttfuzz-1.2.28.dist-info/RECORD
