Metadata-Version: 2.1
Name: muttfuzz
Version: 1.2.28
Summary: Fuzzing with mutants
Home-page: https://github.com/agroce/muttfuzz
License: MIT
Keywords: fuzzing mutation
Platform: UNKNOWN
Classifier: Intended Audience :: Developers
Classifier: Development Status :: 4 - Beta
Classifier: Programming Language :: Python :: 3
